Work13less15/__init__.py
Work13less15/homeWork13.py
Work13less15-0.0.1.dist-info/LICENSE
Work13less15-0.0.1.dist-info/METADATA
Work13less15-0.0.1.dist-info/WHEEL
Work13less15-0.0.1.dist-info/top_level.txt
Work13less15-0.0.1.dist-info/RECORD
