Metadata-Version: 2.1
Name: Work13less15
Version: 0.0.1
Summary: improved table from lesson 13
Home-page: https://github.com/egordavyd/HOMEWORK15
Author: EgorDavydenko
Author-email: egordavydenko1999@mail.ru
Classifier: Programming Language :: Python :: 3.8
Classifier: License :: OSI Approved :: MIT License
Classifier: Operating System :: OS Independent
Requires-Python: >=3.6
License-File: LICENSE
